Workbook

Sheet Lusso Labs Master_Proforma
A1: Lusso Labs | C1: Master_Proforma | N1: 2026
A2: Category | B2: Jan-26 | C2: Feb-26 | D2: Mar-26 | E2: Apr-26 | F2: May-26 | G2: Jun-26 | H2: Jul-26 | I2: Aug-26 | J2: Sep-26 | K2: Oct-26 | L2: Nov-26 | M2: Dec-26 | N2: Total
A3: Revenue | B3: =Revenue_Forecast_Model!B16 -> 0 | C3: =Revenue_Forecast_Model!C16 -> 0 | D3: =Revenue_Forecast_Model!D16 -> 0 | E3: =Revenue_Forecast_Model!E16 -> 0 | F3: =Revenue_Forecast_Model!F16 -> 25000 | G3: =Revenue_Forecast_Model!G16 -> 45000 | H3: =Revenue_Forecast_Model!H16 -> 70000 | I3: =Revenue_Forecast_Model!I16 -> 95000 | ... M3: =Revenue_Forecast_Model!M16 -> 215000 | N3: =SUM(B3:M3) -> 915000
A4: Variable Costs | B4: =IFERROR(B3 * (1 - VALUE(Inputs_Assumptions!$B$5)), 0) -> 0 | C4: =IFERROR(C3 * (1 - VALUE(Inputs_Assumptions!$B$5)), 0) -> 0 | D4: =IFERROR(D3 * (1 - VALUE(Inputs_Assumptions!$B$5)), 0) -> 0 | E4: =IFERROR(E3 * (1 - VALUE(Inputs_Assumptions!$B$5)), 0) -> 0 | F4: =IFERROR(F3 * (1 - VALUE(Inputs_Assumptions!$B$5)), 0) -> 3750 | G4: =IFERROR(G3 * (1 - VALUE(Inputs_Assumptions!$B$5)), 0) -> 6750 | H4: =IFERROR(H3 * (1 - VALUE(Inputs_Assumptions!$B$5)), 0) -> 10500 | I4: =IFERROR(I3 * (1 - VALUE(Inputs_Assumptions!$B$5)), 0) -> 14250 | ... M4: =IFERROR(M3 * (1 - VALUE(Inputs_Assumptions!$B$5)), 0) -> 32250 | N4: =SUM(B4:M4) -> 137250
A5: Gross Profit | B5: =B3-B4 -> 0 | C5: =C3-C4 -> 0 | D5: =D3-D4 -> 0 | E5: =E3-E4 -> 0 | F5: =F3-F4 -> 21250 | G5: =G3-G4 -> 38250 | H5: =H3-H4 -> 59500 | I5: =I3-I4 -> 80750 | ... M5: =M3-M4 -> 182750 | N5: =Sum(B5:M5) -> 777750
A6: Gross Profit % | B6: 0 | C6: 0 | D6: 0 | E6: 0 | F6: 0.9 | G6: 0.9 | H6: 0.9 | I6: 0.9 | J6: 0.9 | K6: 0.9 | L6: 0.9 | M6: 0.9 | N6: 0.9
A7: OPERATING EXPENSES
A8: Direct Labor | B8: 108000 | C8: 108000 | D8: 108000 | E8: 108000 | F8: 108000 | G8: 108000 | H8: 108000 | I8: 108000 | J8: 108000 | K8: 108000 | L8: 108000 | M8: 108000 | N8: =SUM(B8:M8) -> 1296000
A9: Indirect Labor | B9: 3000 | C9: 3000 | D9: 3000 | E9: 3000 | F9: 3000 | G9: 3000 | H9: 3000 | I9: 3000 | J9: 3000 | K9: 3000 | L9: 3000 | M9: 3000 | N9: =SUM(B9:M9) -> 36000
A10: Property | B10: 5916 | C10: 5916 | D10: 5916 | E10: 5916 | F10: 5916 | G10: 5916 | H10: 5916 | I10: 5916 | J10: 5916 | K10: 5916 | L10: 5916 | M10: 5916 | N10: 70992
A11: Utilities | B11: 1120 | C11: 1120 | D11: 1120 | E11: 1120 | F11: 1120 | G11: 1120 | H11: 1120 | I11: 1120 | J11: 1120 | K11: 1120 | L11: 1120 | M11: 1120 | N11: =SUM(B11:M11) -> 13440
A12: Services | B12: 3500 | C12: 3500 | D12: 3500 | E12: 3500 | F12: 3500 | G12: 3500 | H12: 3500 | I12: 3500 | J12: 3500 | K12: 3500 | L12: 3500 | M12: 3500 | N12: =SUM(B12:M12) -> 42000
A13: Office Supplies | B13: 1500 | C13: 1500 | D13: 1500 | E13: 1500 | F13: 1500 | G13: 1500 | H13: 1500 | I13: 1500 | J13: 1500 | K13: 1500 | L13: 1500 | M13: 1500 | N13: =SUM(B13:M13) -> 18000
A14: Technology | B14: 20000 | C14: 20000 | D14: 20000 | E14: 20000 | F14: 25000 | G14: 25000 | H14: 25000 | I14: 25000 | J14: 25000 | K14: 25000 | L14: 25000 | M14: 25000 | N14: =SUM(B14:M14) -> 280000
A15: Marketing | B15: 6251 | C15: 6251 | D15: 6251 | E15: 6251 | F15: 43750 | G15: 43750 | H15: 43750 | I15: 43750 | J15: 75000 | K15: 75000 | L15: 75000 | M15: 75000 | N15: =SUM(B15:M15) -> 500004
A16: Total Expenses | B16: =SUM(B8:B15) -> 149287 | C16: =SUM(C8:C15) -> 149287 | D16: =SUM(D8:D15) -> 149287 | E16: =SUM(E8:E15) -> 149287 | F16: =SUM(F8:F15) -> 191786 | G16: =SUM(G8:G15) -> 191786 | H16: =SUM(H8:H15) -> 191786 | I16: =SUM(I8:I15) -> 191786 | ... M16: =SUM(M8:M15) -> 223036 | N16: =SUM(B16:M16) -> 2256436
A17: Operating Expense % | B17: =IFERROR(B16/B3,0) -> 0 | C17: =IFERROR(C16/C3,0) -> 0 | D17: =IFERROR(D16/D3,0) -> 0 | E17: =IFERROR(E16/E3,0) -> 0 | F17: =IFERROR(F16/F3,0) -> 7.67144 | G17: =IFERROR(G16/G3,0) -> 4.2619111 | H17: =IFERROR(H16/H3,0) -> 2.7398 | I17: =IFERROR(I16/I3,0) -> 2.0188 | ... N17: =IFERROR(N16/N3,0) -> 2.4660503
A18: EBITDA | B18: =B5-B16 -> -149287 | C18: =C5-C16 -> -149287 | D18: =D5-D16 -> -149287 | E18: =E5-E16 -> -149287 | F18: =F5-F16 -> -170536 | G18: =G5-G16 -> -153536 | H18: =H5-H16 -> -132286 | I18: =I5-I16 -> -111036 | ... M18: =M5-M16 -> -40286 | N18: =SUM(B18:M18) -> -1478686
A19: EBITDA % | B19: =IFERROR(B18/B3,0) -> 0 | C19: =IFERROR(C18/C3,0) -> 0 | D19: =IFERROR(D18/D3,0) -> 0 | E19: =IFERROR(E18/E3,0) -> 0 | F19: =IFERROR(F18/F3,0) -> -6.82144 | G19: =IFERROR(G18/G3,0) -> -3.4119111 | H19: =IFERROR(H18/H3,0) -> -1.8898 | I19: =IFERROR(I18/I3,0) -> -1.1688 | ... N19: =IFERROR(N18/N3,0) -> -1.6160503
A21: Lusso Labs Master_Proforma 2026
A22: Page 1 of 1 02/05/26

Sheet Master_Proforma
A1: Lusso Labs - Master Proforma (24 Months)
A3: Category | B3: Jan-26 | C3: Feb-26 | D3: Mar-26 | E3: Apr-26 | F3: May-26 | G3: Jun-26 | H3: Jul-26 | I3: Aug-26 | J3: Sep-26 | K3: Oct-26 | L3: Nov-26 | M3: Dec-26 | N3: Jan-27 | O3: Feb-27 | P3: Mar-27 | Q3: Apr-27 | R3: May-27 | S3: Jun-27 | T3: Jul-27 | U3: Aug-27 | V3: Sep-27 | W3: Oct-27 | X3: Nov-27 | Y3: Dec-27 | Z3: Total
A4: Revenue | B4: =Inputs_Assumptions!$E$5 -> 0 | C4: =Inputs_Assumptions!$E$6 -> 0 | D4: =Inputs_Assumptions!$E$7 -> 0 | E4: =Inputs_Assumptions!$E$8 -> 0 | F4: =Inputs_Assumptions!$E$9 -> 25000 | G4: =Inputs_Assumptions!$E$10 -> 45000 | H4: =Inputs_Assumptions!$E$11 -> 70000 | I4: =Inputs_Assumptions!$E$12 -> 95000 | J4: =Inputs_Assumptions!$E$13 -> 125000 | K4: =Inputs_Assumptions!$E$14 -> 155000 | L4: =Inputs_Assumptions!$E$15 -> 185000 | M4: =Inputs_Assumptions!$E$16 -> 215000 | N4: =Inputs_Assumptions!$E$17 -> 280000 | O4: =Inputs_Assumptions!$E$18 -> 310000 | P4: =Inputs_Assumptions!$E$19 -> 345000 | Q4: =Inputs_Assumptions!$E$20 -> 385000 | R4: =Inputs_Assumptions!$E$21 -> 430000 | S4: =Inputs_Assumptions!$E$22 -> 480000 | T4: =Inputs_Assumptions!$E$23 -> 530000 | U4: =Inputs_Assumptions!$E$24 -> 590000 | V4: =Inputs_Assumptions!$E$25 -> 660000 | W4: =Inputs_Assumptions!$E$26 -> 740000 | X4: =Inputs_Assumptions!$E$27 -> 830000 | Y4: =Inputs_Assumptions!$E$28 -> 930000 | Z4: =SUM(B4:Y4) -> 7425000
A5: AI / Usage COGS | B5: =B4*(1-Inputs_Assumptions!$B$5) -> 0 | C5: =C4*(1-Inputs_Assumptions!$B$5) -> 0 | D5: =D4*(1-Inputs_Assumptions!$B$5) -> 0 | E5: =E4*(1-Inputs_Assumptions!$B$5) -> 0 | F5: =F4*(1-Inputs_Assumptions!$B$5) -> 3750 | G5: =G4*(1-Inputs_Assumptions!$B$5) -> 6750 | H5: =H4*(1-Inputs_Assumptions!$B$5) -> 10500 | I5: =I4*(1-Inputs_Assumptions!$B$5) -> 14250 | ... Y5: =Y4*(1-Inputs_Assumptions!$B$5) -> 139500 | Z5: =SUM(B5:Y5) -> 1113750
A6: Gross Profit | B6: =B4-B5 -> 0 | C6: =C4-C5 -> 0 | D6: =D4-D5 -> 0 | E6: =E4-E5 -> 0 | F6: =F4-F5 -> 21250 | G6: =G4-G5 -> 38250 | H6: =H4-H5 -> 59500 | I6: =I4-I5 -> 80750 | ... Y6: =Y4-Y5 -> 790500 | Z6: =SUM(B6:Y6) -> 6311250
A7: Gross Profit % | B7: =IFERROR(B6/B4,0) -> 0 | C7: =IFERROR(C6/C4,0) -> 0 | D7: =IFERROR(D6/D4,0) -> 0 | E7: =IFERROR(E6/E4,0) -> 0 | F7: =IFERROR(F6/F4,0) -> 0.85 | G7: =IFERROR(G6/G4,0) -> 0.85 | H7: =IFERROR(H6/H4,0) -> 0.85 | I7: =IFERROR(I6/I4,0) -> 0.85 | ... Z7: =IFERROR(Z6/Z4,0) -> 0.85
A9: OPERATING EXPENSES
A10: People | B10: 108000 | C10: 108000 | D10: 108000 | E10: 108000 | F10: 108000 | G10: 108000 | H10: 108000 | I10: 108000 | J10: 108000 | K10: 108000 | L10: 108000 | M10: 108000 | N10: 108000 | O10: 108000 | P10: 108000 | Q10: 115000 | R10: 115000 | S10: 115000 | T10: 125000 | U10: 125000 | V10: 125000 | W10: 125000 | X10: 125000 | Y10: 125000 | Z10: =SUM(B10:Y10) -> 2715000
A11: Tech / AI / Cloud (Fixed) | B11: 45000 | C11: 45000 | D11: 45000 | E11: 45000 | F11: 45000 | G11: 45000 | H11: 45000 | I11: 45000 | J11: 45000 | K11: 45000 | L11: 45000 | M11: 45000 | N11: 50000 | O11: 50000 | P11: 50000 | Q11: 50000 | R11: 50000 | S11: 50000 | T11: 50000 | U11: 50000 | V11: 50000 | W11: 50000 | X11: 50000 | Y11: 50000 | Z11: =SUM(B11:Y11) -> 1140000
A12: Marketing & Growth | B12: 0 | C12: 0 | D12: 0 | E12: 0 | F12: 0 | G12: 0 | H12: 0 | I12: 0 | J12: 0 | K12: 0 | L12: 0 | M12: 0 | N12: 27000 | O12: 32909.091 | P12: 38818.182 | Q12: 37727.273 | R12: 43636.364 | S12: 49545.455 | T12: 45454.545 | U12: 51363.636 | V12: 57272.727 | W12: 63181.818 | X12: 69090.909 | Y12: 75000 | Z12: =SUM(B12:Y12) -> 591000
A13: Legal / Ops / Buffer | B13: 7000 | C13: 7000 | D13: 7000 | E13: 7000 | F13: 7000 | G13: 7000 | H13: 7000 | I13: 7000 | J13: 7000 | K13: 7000 | L13: 7000 | M13: 7000 | N13: 10000 | O13: 10000 | P13: 10000 | Q13: 10000 | R13: 10000 | S13: 10000 | T13: 10000 | U13: 10000 | V13: 10000 | W13: 10000 | X13: 10000 | Y13: 10000 | Z13: =SUM(B13:Y13) -> 204000
A14: Total Expenses | B14: =SUM(B10:B13) -> 160000 | C14: =SUM(C10:C13) -> 160000 | D14: =SUM(D10:D13) -> 160000 | E14: =SUM(E10:E13) -> 160000 | F14: =SUM(F10:F13) -> 160000 | G14: =SUM(G10:G13) -> 160000 | H14: =SUM(H10:H13) -> 160000 | I14: =SUM(I10:I13) -> 160000 | ... Y14: =SUM(Y10:Y13) -> 260000 | Z14: =SUM(B14:Y14) -> 4650000
A15: Operating Expense % | B15: =IFERROR(B14/B4,0) -> 0 | C15: =IFERROR(C14/C4,0) -> 0 | D15: =IFERROR(D14/D4,0) -> 0 | E15: =IFERROR(E14/E4,0) -> 0 | F15: =IFERROR(F14/F4,0) -> 6.4 | G15: =IFERROR(G14/G4,0) -> 3.5555556 | H15: =IFERROR(H14/H4,0) -> 2.2857143 | I15: =IFERROR(I14/I4,0) -> 1.6842105 | ... Z15: =IFERROR(Z14/Z4,0) -> 0.62626263
A16: EBITDA | B16: =B6-B14 -> -160000 | C16: =C6-C14 -> -160000 | D16: =D6-D14 -> -160000 | E16: =E6-E14 -> -160000 | F16: =F6-F14 -> -138750 | G16: =G6-G14 -> -121750 | H16: =H6-H14 -> -100500 | I16: =I6-I14 -> -79250 | ... Y16: =Y6-Y14 -> 530500 | Z16: =SUM(B16:Y16) -> 1661250
A17: EBITDA % | B17: =IFERROR(B16/B4,0) -> 0 | C17: =IFERROR(C16/C4,0) -> 0 | D17: =IFERROR(D16/D4,0) -> 0 | E17: =IFERROR(E16/E4,0) -> 0 | F17: =IFERROR(F16/F4,0) -> -5.55 | G17: =IFERROR(G16/G4,0) -> -2.7055556 | H17: =IFERROR(H16/H4,0) -> -1.4357143 | I17: =IFERROR(I16/I4,0) -> -0.83421053 | ... Z17: =IFERROR(Z16/Z4,0) -> 0.22373737

Sheet Revenue Forecast Model
A1: Revenue Forecast Model
A3: Ask Lusso - Consumer
A4: Blended ARPU | B4: 38 | C4: Launches Month 5 (May) | Target: 8,500 users by Dec
A5: Jan-26 | B5: Feb-26 | C5: Mar-26 | D5: Apr-26 | E5: May-26 | F5: Jun-26 | G5: Jul-26 | H5: Aug-26 | I5: Sep-26 | J5: Oct-26 | K5: Nov-26 | L5: Dec-26
A6: 0 | B6: 0 | C6: 0 | D6: 0 | E6: 800 | F6: 1500 | G6: 2400 | H6: 3500 | I6: 4800 | J6: 6200 | K6: 7500 | L6: 8500
A7: 0 | B7: 0 | C7: 0 | D7: 0 | E7: 30400 | F7: 57000 | G7: 91200 | H7: 133000 | I7: 182400 | J7: 235600 | K7: 285000 | L7: 323000
A9: Ask Lusso - Business
A10: ARPU | B10: 175 | C10: Launches Month 5 (May) | Target: 1,500 accounts by Dec
A11: Jan-26 | B11: Feb-26 | C11: Mar-26 | D11: Apr-26 | E11: May-26 | F11: Jun-26 | G11: Jul-26 | H11: Aug-26 | I11: Sep-26 | J11: Oct-26 | K11: Nov-26 | L11: Dec-26
A12: 0 | B12: 0 | C12: 0 | D12: 0 | E12: 150 | F12: 300 | G12: 500 | H12: 750 | I12: 1000 | J12: 1200 | K12: 1350 | L12: 1500
A13: 0 | B13: 0 | C13: 0 | D13: 0 | E13: 26250 | F13: 52500 | G13: 87500 | H13: 131250 | I13: 175000 | J13: 210000 | K13: 236250 | L13: 262500
A15: Marketplace - Sellers
A16: Revenue per Seller | B16: 285 | C16: Launches Month 8 (Aug) | Target: 1,200 sellers by Dec | D16: $125 sub + $160 fees
A17: Jan-26 | B17: Feb-26 | C17: Mar-26 | D17: Apr-26 | E17: May-26 | F17: Jun-26 | G17: Jul-26 | H17: Aug-26 | I17: Sep-26 | J17: Oct-26 | K17: Nov-26 | L17: Dec-26
A18: 0 | B18: 0 | C18: 0 | D18: 0 | E18: 0 | F18: 0 | G18: 0 | H18: 200 | I18: 400 | J18: 700 | K18: 950 | L18: 1200
A19: 0 | B19: 0 | C19: 0 | D19: 0 | E19: 0 | F19: 0 | G19: 0 | H19: 57000 | I19: 114000 | J19: 199500 | K19: 270750 | L19: 342000
A21: TOTAL MONTHLY REVENUE
A22: 0 | B22: 0 | C22: 0 | D22: 0 | E22: 56650 | F22: 109500 | G22: 178700 | H22: 321250 | I22: 471400 | J22: 645100 | K22: 792000 | L22: 927500

Sheet Tech_AI_Cloud
A1: Tech / AI / Cloud Detail (Monthly)
A3: Category | B3: Jan-26 | C3: Feb-26 | D3: Mar-26 | E3: Apr-26 | F3: May-26 | G3: Jun-26 | H3: Jul-26 | I3: Aug-26 | J3: Sep-26 | K3: Oct-26 | L3: Nov-26 | M3: Dec-26 | N3: Jan-27 | O3: Feb-27 | P3: Mar-27 | Q3: Apr-27 | R3: May-27 | S3: Jun-27 | T3: Jul-27 | U3: Aug-27 | V3: Sep-27 | W3: Oct-27 | X3: Nov-27 | Y3: Dec-27 | Z3: Total
A4: Cloud Hosting (base) | B4: 6000 | C4: 6000 | D4: 6000 | E4: 6000 | F4: 7500 | G4: 7500 | H4: 7500 | I4: 7500 | J4: 7500 | K4: 7500 | L4: 7500 | M4: 7500 | N4: 7500 | O4: 7500 | P4: 7500 | Q4: 14705.88 | R4: 14705.88 | S4: 14705.88 | T4: 14705.88 | U4: 14705.88 | V4: 14705.88 | W4: 14705.88 | X4: 14705.88 | Y4: 14705.88 | Z4: =SUM(B4:Y4) -> 238852.92
A5: GPU / Inference (base) | B5: 7000 | C5: 7000 | D5: 7000 | E5: 7000 | F5: 8750 | G5: 8750 | H5: 8750 | I5: 8750 | J5: 8750 | K5: 8750 | L5: 8750 | M5: 8750 | N5: 8750 | O5: 8750 | P5: 8750 | Q5: 17647.06 | R5: 17647.06 | S5: 17647.06 | T5: 17647.06 | U5: 17647.06 | V5: 17647.06 | W5: 17647.06 | X5: 17647.06 | Y5: 17647.06 | Z5: =SUM(B5:Y5) -> 283073.54
A6: LLM API Usage (base) | B6: 4000 | C6: 4000 | D6: 4000 | E6: 4000 | F6: 5000 | G6: 5000 | H6: 5000 | I6: 5000 | J6: 5000 | K6: 5000 | L6: 5000 | M6: 5000 | N6: 5000 | O6: 5000 | P6: 5000 | Q6: 11764.71 | R6: 11764.71 | S6: 11764.71 | T6: 11764.71 | U6: 11764.71 | V6: 11764.71 | W6: 11764.71 | X6: 11764.71 | Y6: 11764.71 | Z6: =SUM(B6:Y6) -> 176882.39
A7: Databases / Storage (base) | B7: 2000 | C7: 2000 | D7: 2000 | E7: 2000 | F7: 2500 | G7: 2500 | H7: 2500 | I7: 2500 | J7: 2500 | K7: 2500 | L7: 2500 | M7: 2500 | N7: 2500 | O7: 2500 | P7: 2500 | Q7: 2941.18 | R7: 2941.18 | S7: 2941.18 | T7: 2941.18 | U7: 2941.18 | V7: 2941.18 | W7: 2941.18 | X7: 2941.18 | Y7: 2941.18 | Z7: =SUM(B7:Y7) -> 61970.62
A8: Monitoring / Security (base) | B8: 1000 | C8: 1000 | D8: 1000 | E8: 1000 | F8: 1250 | G8: 1250 | H8: 1250 | I8: 1250 | J8: 1250 | K8: 1250 | L8: 1250 | M8: 1250 | N8: 1250 | O8: 1250 | P8: 1250 | Q8: 2941.18 | R8: 2941.18 | S8: 2941.18 | T8: 2941.18 | U8: 2941.18 | V8: 2941.18 | W8: 2941.18 | X8: 2941.18 | Y8: 2941.18 | Z8: =SUM(B8:Y8) -> 44220.62
A10: Subtotal | B10: =SUM(B4:B9) -> 20000 | C10: =SUM(C4:C9) -> 20000 | D10: =SUM(D4:D9) -> 20000 | E10: =SUM(E4:E9) -> 20000 | F10: =SUM(F4:F9) -> 25000 | G10: =SUM(G4:G9) -> 25000 | H10: =SUM(H4:H9) -> 25000 | I10: =SUM(I4:I9) -> 25000 | ... Y10: =SUM(Y4:Y9) -> 50000.01 | Z10: =SUM(B10:Y10) -> 805000.09

Sheet Inputs_Assumptions
A1: LUSSO.AI - Proforma Inputs (edit yellow cells)
A3: Input | B3: Value | D3: Phase Revenue Targets | G3: Revenue Mix Assumptions (shares by phase)
A4: Starting Cash | B4: 2500000 | D4: Month # | E4: Total Revenue / MRR | G4: Phase | H4: Months | I4: Consumer % | J4: Business % | K4: Marketplace %
A5: Gross Margin % (for AI/usage COGS) | B5: 0.85 | D5: 1 | E5: 0 | G5: Pre-launch | H5: 1-4 | I5: 0 | J5: 0 | K5: 0
A6: Consumer ARPU (blended) - early | B6: 38 | D6: 2 | E6: 0 | G6: Ask Lusso launch | H6: 5-7 | I6: 1 | J6: 0 | K6: 0
A7: Consumer ARPU (blended) - Month 13+ | B7: 42 | D7: 3 | E7: 0 | G7: Biz ramp | H7: 8-9 | I7: 0.7 | J7: 0.3 | K7: 0
A8: Business ARPU | B8: 175 | D8: 4 | E8: 0 | G8: Pre-marketplace | H8: 10-12 | I8: 0.6 | J8: 0.4 | K8: 0
A9: Marketplace Seller ARPU (sub + fees blended) | B9: 285 | D9: 5 | E9: 25000 | G9: Marketplace live | H9: 13-24 | I9: 0.38 | J9: 0.27 | K9: 0.35
A10: Marketplace Transaction Fee % (info) | B10: 0.08 | D10: 6 | E10: 45000
A11: Ask Lusso Weekly Price (info) | B11: 8.99 | D11: 7 | E11: 70000
A12: Ask Lusso Monthly Price (info) | B12: 28.99 | D12: 8 | E12: 95000
A13: Ask Lusso Premium Price (info) | B13: 49.99 | D13: 9 | E13: 125000
D14: 10 | E14: 155000
D15: 11 | E15: 185000
D16: 12 | E16: 215000
D17: 13 | E17: 280000
D18: 14 | E18: 310000
D19: 15 | E19: 345000
D20: 16 | E20: 385000
D21: 17 | E21: 430000
D22: 18 | E22: 480000
D23: 19 | E23: 530000
D24: 20 | E24: 590000
D25: 21 | E25: 660000
... D28: 24 | E28: 930000

Sheet Revenue_Forecast_Model
A1: Revenue Forecast Model (Ask Lusso + Marketplace)
A3: Category | B3: Jan-26 | C3: Feb-26 | D3: Mar-26 | E3: Apr-26 | F3: May-26 | G3: Jun-26 | H3: Jul-26 | I3: Aug-26 | J3: Sep-26 | K3: Oct-26 | L3: Nov-26 | M3: Dec-26 | N3: Jan-27 | O3: Feb-27 | P3: Mar-27 | Q3: Apr-27 | R3: May-27 | S3: Jun-27 | T3: Jul-27 | U3: Aug-27 | V3: Sep-27 | W3: Oct-27 | X3: Nov-27 | Y3: Dec-27 | Z3: Total
A4: Ask Lusso - Consumer ARPU | B4: =IF(1>=13,Inputs_Assumptions!$B$7,Inputs_Assumptions!$B$6) -> 38 | C4: =IF(2>=13,Inputs_Assumptions!$B$7,Inputs_Assumptions!$B$6) -> 38 | D4: =IF(3>=13,Inputs_Assumptions!$B$7,Inputs_Assumptions!$B$6) -> 38 | E4: =IF(4>=13,Inputs_Assumptions!$B$7,Inputs_Assumptions!$B$6) -> 38 | F4: =IF(5>=13,Inputs_Assumptions!$B$7,Inputs_Assumptions!$B$6) -> 38 | G4: =IF(6>=13,Inputs_Assumptions!$B$7,Inputs_Assumptions!$B$6) -> 38 | H4: =IF(7>=13,Inputs_Assumptions!$B$7,Inputs_Assumptions!$B$6) -> 38 | I4: =IF(8>=13,Inputs_Assumptions!$B$7,Inputs_Assumptions!$B$6) -> 38 | J4: =IF(9>=13,Inputs_Assumptions!$B$7,Inputs_Assumptions!$B$6) -> 38 | K4: =IF(10>=13,Inputs_Assumptions!$B$7,Inputs_Assumptions!$B$6) -> 38 | L4: =IF(11>=13,Inputs_Assumptions!$B$7,Inputs_Assumptions!$B$6) -> 38 | M4: =IF(12>=13,Inputs_Assumptions!$B$7,Inputs_Assumptions!$B$6) -> 38 | N4: =IF(13>=13,Inputs_Assumptions!$B$7,Inputs_Assumptions!$B$6) -> 42 | O4: =IF(14>=13,Inputs_Assumptions!$B$7,Inputs_Assumptions!$B$6) -> 42 | P4: =IF(15>=13,Inputs_Assumptions!$B$7,Inputs_Assumptions!$B$6) -> 42 | Q4: =IF(16>=13,Inputs_Assumptions!$B$7,Inputs_Assumptions!$B$6) -> 42 | R4: =IF(17>=13,Inputs_Assumptions!$B$7,Inputs_Assumptions!$B$6) -> 42 | S4: =IF(18>=13,Inputs_Assumptions!$B$7,Inputs_Assumptions!$B$6) -> 42 | T4: =IF(19>=13,Inputs_Assumptions!$B$7,Inputs_Assumptions!$B$6) -> 42 | U4: =IF(20>=13,Inputs_Assumptions!$B$7,Inputs_Assumptions!$B$6) -> 42 | V4: =IF(21>=13,Inputs_Assumptions!$B$7,Inputs_Assumptions!$B$6) -> 42 | W4: =IF(22>=13,Inputs_Assumptions!$B$7,Inputs_Assumptions!$B$6) -> 42 | X4: =IF(23>=13,Inputs_Assumptions!$B$7,Inputs_Assumptions!$B$6) -> 42 | Y4: =IF(24>=13,Inputs_Assumptions!$B$7,Inputs_Assumptions!$B$6) -> 42
A5: Ask Lusso - Business ARPU | B5: =Inputs_Assumptions!$B$8 -> 175 | C5: =Inputs_Assumptions!$B$8 -> 175 | D5: =Inputs_Assumptions!$B$8 -> 175 | E5: =Inputs_Assumptions!$B$8 -> 175 | F5: =Inputs_Assumptions!$B$8 -> 175 | G5: =Inputs_Assumptions!$B$8 -> 175 | H5: =Inputs_Assumptions!$B$8 -> 175 | I5: =Inputs_Assumptions!$B$8 -> 175 | ... Y5: =Inputs_Assumptions!$B$8 -> 175
A6: Marketplace - Seller ARPU | B6: =Inputs_Assumptions!$B$9 -> 285 | C6: =Inputs_Assumptions!$B$9 -> 285 | D6: =Inputs_Assumptions!$B$9 -> 285 | E6: =Inputs_Assumptions!$B$9 -> 285 | F6: =Inputs_Assumptions!$B$9 -> 285 | G6: =Inputs_Assumptions!$B$9 -> 285 | H6: =Inputs_Assumptions!$B$9 -> 285 | I6: =Inputs_Assumptions!$B$9 -> 285 | ... Y6: =Inputs_Assumptions!$B$9 -> 285
A8: Consumer % (by phase) | B8: 0 | C8: 0 | D8: 0 | E8: 0 | F8: 1 | G8: 1 | H8: 1 | I8: 0.7 | J8: 0.7 | K8: 0.6 | L8: 0.6 | M8: 0.6 | N8: 0.38 | O8: 0.38 | P8: 0.38 | Q8: 0.38 | R8: 0.38 | S8: 0.38 | T8: 0.38 | U8: 0.38 | V8: 0.38 | W8: 0.38 | X8: 0.38 | Y8: 0.38
A9: Business % (by phase) | B9: 0 | C9: 0 | D9: 0 | E9: 0 | F9: 0 | G9: 0 | H9: 0 | I9: 0.3 | J9: 0.3 | K9: 0.4 | L9: 0.4 | M9: 0.4 | N9: 0.27 | O9: 0.27 | P9: 0.27 | Q9: 0.27 | R9: 0.27 | S9: 0.27 | T9: 0.27 | U9: 0.27 | V9: 0.27 | W9: 0.27 | X9: 0.27 | Y9: 0.27
A10: Marketplace % (by phase) | B10: 0 | C10: 0 | D10: 0 | E10: 0 | F10: 0 | G10: 0 | H10: 0 | I10: 0 | J10: 0 | K10: 0 | L10: 0 | M10: 0 | N10: 0.35 | O10: 0.35 | P10: 0.35 | Q10: 0.35 | R10: 0.35 | S10: 0.35 | T10: 0.35 | U10: 0.35 | V10: 0.35 | W10: 0.35 | X10: 0.35 | Y10: 0.35
A12: Consumer Revenue | B12: =B16*B8 -> 0 | C12: =C16*C8 -> 0 | D12: =D16*D8 -> 0 | E12: =E16*E8 -> 0 | F12: =F16*F8 -> 25000 | G12: =G16*G8 -> 45000 | H12: =H16*H8 -> 70000 | I12: =I16*I8 -> 66500 | ... Y12: =Y16*Y8 -> 353400 | Z12: =SUM(B12:Y12) -> 3100800
A13: Business Revenue | B13: =B16*B9 -> 0 | C13: =C16*C9 -> 0 | D13: =D16*D9 -> 0 | E13: =E16*E9 -> 0 | F13: =F16*F9 -> 0 | G13: =G16*G9 -> 0 | H13: =H16*H9 -> 0 | I13: =I16*I9 -> 28500 | ... Y13: =Y16*Y9 -> 251100 | Z13: =SUM(B13:Y13) -> 2045700
A14: Marketplace Revenue | B14: =B16*B10 -> 0 | C14: =C16*C10 -> 0 | D14: =D16*D10 -> 0 | E14: =E16*E10 -> 0 | F14: =F16*F10 -> 0 | G14: =G16*G10 -> 0 | H14: =H16*H10 -> 0 | I14: =I16*I10 -> 0 | ... Y14: =Y16*Y10 -> 325500 | Z14: =SUM(B14:Y14) -> 2278500
A16: TOTAL MONTHLY REVENUE | B16: =Master_Proforma!B4 -> 0 | C16: =Master_Proforma!C4 -> 0 | D16: =Master_Proforma!D4 -> 0 | E16: =Master_Proforma!E4 -> 0 | F16: =Master_Proforma!F4 -> 25000 | G16: =Master_Proforma!G4 -> 45000 | H16: =Master_Proforma!H4 -> 70000 | I16: =Master_Proforma!I4 -> 95000 | ... Y16: =Master_Proforma!Y4 -> 930000 | Z16: =SUM(B16:Y16) -> 7425000
A19: Implied Paying Consumers | B19: =IFERROR(B12/B4,0) -> 0 | C19: =IFERROR(C12/C4,0) -> 0 | D19: =IFERROR(D12/D4,0) -> 0 | E19: =IFERROR(E12/E4,0) -> 0 | F19: =IFERROR(F12/F4,0) -> 657.89474 | G19: =IFERROR(G12/G4,0) -> 1184.2105 | H19: =IFERROR(H12/H4,0) -> 1842.1053 | I19: =IFERROR(I12/I4,0) -> 1750 | ... Y19: =IFERROR(Y12/Y4,0) -> 8414.2857 | Z19: =AVERAGE(B19:Y19) -> 3141.6667
A20: Implied Business Accounts | B20: =IFERROR(B13/B5,0) -> 0 | C20: =IFERROR(C13/C5,0) -> 0 | D20: =IFERROR(D13/D5,0) -> 0 | E20: =IFERROR(E13/E5,0) -> 0 | F20: =IFERROR(F13/F5,0) -> 0 | G20: =IFERROR(G13/G5,0) -> 0 | H20: =IFERROR(H13/H5,0) -> 0 | I20: =IFERROR(I13/I5,0) -> 162.85714 | ... Y20: =IFERROR(Y13/Y5,0) -> 1434.8571 | Z20: =AVERAGE(B20:Y20) -> 487.07143
A21: Implied Marketplace Sellers | B21: =IFERROR(B14/B6,0) -> 0 | C21: =IFERROR(C14/C6,0) -> 0 | D21: =IFERROR(D14/D6,0) -> 0 | E21: =IFERROR(E14/E6,0) -> 0 | F21: =IFERROR(F14/F6,0) -> 0 | G21: =IFERROR(G14/G6,0) -> 0 | H21: =IFERROR(H14/H6,0) -> 0 | I21: =IFERROR(I14/I6,0) -> 0 | ... Y21: =IFERROR(Y14/Y6,0) -> 1142.1053 | Z21: =AVERAGE(B21:Y21) -> 333.11404

Sheet Marketing_Growth
A1: Marketing & Growth Detail (Monthly)
A3: Category | B3: Jan-26 | C3: Feb-26 | D3: Mar-26 | E3: Apr-26 | F3: May-26 | G3: Jun-26 | H3: Jul-26 | I3: Aug-26 | J3: Sep-26 | K3: Oct-26 | L3: Nov-26 | M3: Dec-26 | N3: Jan-27 | O3: Feb-27 | P3: Mar-27 | Q3: Apr-27 | R3: May-27 | S3: Jun-27 | T3: Jul-27 | U3: Aug-27 | V3: Sep-27 | W3: Oct-27 | X3: Nov-27 | Y3: Dec-27 | Z3: Total
A4: Paid Ads (Consumer) | B4: 2500 | C4: 2500 | D4: 2500 | E4: 2500 | F4: 17500 | G4: 17500 | H4: 17500 | I4: 17500 | J4: 30000 | K4: 30000 | L4: 30000 | M4: 30000 | N4: 23850 | O4: 23850 | P4: 23850 | Q4: 18972 | R4: 18972 | S4: 18972 | T4: 15091.2 | U4: 15091.2 | V4: 15091.2 | W4: 12000 | X4: 12000 | Y4: 12000 | Z4: =SUM(B4:Y4) -> 409739.6
A5: Paid Ads (Business) | B5: 1875 | C5: 1875 | D5: 1875 | E5: 1875 | F5: 13125 | G5: 13125 | H5: 13125 | I5: 13125 | J5: 22500 | K5: 22500 | L5: 22500 | M5: 22500 | N5: 17887.5 | O5: 17887.5 | P5: 17887.5 | Q5: 14229 | R5: 14229 | S5: 14229 | T5: 11318.4 | U5: 11318.4 | V5: 11318.4 | W5: 9000 | X5: 9000 | Y5: 9000 | Z5: =SUM(B5:Y5) -> 307304.7
A6: Influencers / Creators | B6: 938 | C6: 938 | D6: 938 | E6: 938 | F6: 6563 | G6: 6563 | H6: 6563 | I6: 6563 | J6: 11250 | K6: 11250 | L6: 11250 | M6: 11250 | N6: 8943.75 | O6: 8943.75 | P6: 8943.75 | Q6: 7114.5 | R6: 7114.5 | S6: 7114.5 | T6: 5659.2 | U6: 5659.2 | V6: 5659.2 | W6: 4500 | X6: 4500 | Y6: 4500 | Z6: =SUM(B6:Y6) -> 153656.35
A7: Launch PR / Content | B7: 625 | C7: 625 | D7: 625 | E7: 625 | F7: 4375 | G7: 4375 | H7: 4375 | I7: 4375 | J7: 7500 | K7: 7500 | L7: 7500 | M7: 7500 | N7: 5962.5 | O7: 5962.5 | P7: 5962.5 | Q7: 4743 | R7: 4743 | S7: 4743 | T7: 3772.8 | U7: 3772.8 | V7: 3772.8 | W7: 3000 | X7: 3000 | Y7: 3000 | Z7: =SUM(B7:Y7) -> 102434.9
A8: Referral Incentives | B8: 313 | C8: 313 | D8: 313 | E8: 313 | F8: 2187 | G8: 2187 | H8: 2187 | I8: 2187 | J8: 3750 | K8: 3750 | L8: 3750 | M8: 3750 | N8: 2981.25 | O8: 2981.25 | P8: 2981.25 | Q8: 2371.5 | R8: 2371.5 | S8: 2371.5 | T8: 1886.4 | U8: 1886.4 | V8: 1886.4 | W8: 1500 | X8: 1500 | Y8: 1500 | Z8: =SUM(B8:Y8) -> 51217.45
A10: Subtotal | B10: =SUM(B4:B9) -> 6251 | C10: =SUM(C4:C9) -> 6251 | D10: =SUM(D4:D9) -> 6251 | E10: =SUM(E4:E9) -> 6251 | F10: =SUM(F4:F9) -> 43750 | G10: =SUM(G4:G9) -> 43750 | H10: =SUM(H4:H9) -> 43750 | I10: =SUM(I4:I9) -> 43750 | ... Y10: =SUM(Y4:Y9) -> 30000 | Z10: =SUM(B10:Y10) -> 1024353

Sheet People
A1: People Cost Detail (Monthly)
A3: Category | B3: Jan-26 | C3: Feb-26 | D3: Mar-26 | E3: Apr-26 | F3: May-26 | G3: Jun-26 | H3: Jul-26 | I3: Aug-26 | J3: Sep-26 | K3: Oct-26 | L3: Nov-26 | M3: Dec-26 | N3: Jan-27 | O3: Feb-27 | P3: Mar-27 | Q3: Apr-27 | R3: May-27 | S3: Jun-27 | T3: Jul-27 | U3: Aug-27 | V3: Sep-27 | W3: Oct-27 | X3: Nov-27 | Y3: Dec-27 | Z3: Total
A4: CTO (hands-on) | B4: 18000 | C4: 18000 | D4: 18000 | E4: 18000 | F4: 18000 | G4: 18000 | H4: 18000 | I4: 18000 | J4: 18000 | K4: 18000 | L4: 18000 | M4: 18000 | N4: 18000 | O4: 18000 | P4: 18000 | Q4: 18000 | R4: 18000 | S4: 18000 | T4: 18000 | U4: 18000 | V4: 18000 | W4: 18000 | X4: 18000 | Y4: 18000 | Z4: =SUM(B4:Y4) -> 432000
A5: Senior Engineer #1 | B5: 15000 | C5: 15000 | D5: 15000 | E5: 15000 | F5: 15000 | G5: 15000 | H5: 15000 | I5: 15000 | J5: 15000 | K5: 15000 | L5: 15000 | M5: 15000 | N5: 15000 | O5: 15000 | P5: 15000 | Q5: 15000 | R5: 15000 | S5: 15000 | T5: 15000 | U5: 15000 | V5: 15000 | W5: 15000 | X5: 15000 | Y5: 15000 | Z5: =SUM(B5:Y5) -> 360000
A6: Senior Engineer #2 | B6: 15000 | C6: 15000 | D6: 15000 | E6: 15000 | F6: 15000 | G6: 15000 | H6: 15000 | I6: 15000 | J6: 15000 | K6: 15000 | L6: 15000 | M6: 15000 | N6: 15000 | O6: 15000 | P6: 15000 | Q6: 15000 | R6: 15000 | S6: 15000 | T6: 15000 | U6: 15000 | V6: 15000 | W6: 15000 | X6: 15000 | Y6: 15000 | Z6: =SUM(B6:Y6) -> 360000
A7: AI Engineer | B7: 16000 | C7: 16000 | D7: 16000 | E7: 16000 | F7: 16000 | G7: 16000 | H7: 16000 | I7: 16000 | J7: 16000 | K7: 16000 | L7: 16000 | M7: 16000 | N7: 16000 | O7: 16000 | P7: 16000 | Q7: 16000 | R7: 16000 | S7: 16000 | T7: 16000 | U7: 16000 | V7: 16000 | W7: 16000 | X7: 16000 | Y7: 16000 | Z7: =SUM(B7:Y7) -> 384000
A8: Product Manager | B8: 12000 | C8: 12000 | D8: 12000 | E8: 12000 | F8: 12000 | G8: 12000 | H8: 12000 | I8: 12000 | J8: 12000 | K8: 12000 | L8: 12000 | M8: 12000 | N8: 12000 | O8: 12000 | P8: 12000 | Q8: 12000 | R8: 12000 | S8: 12000 | T8: 12000 | U8: 12000 | V8: 12000 | W8: 12000 | X8: 12000 | Y8: 12000 | Z8: =SUM(B8:Y8) -> 288000
A9: Growth Lead | B9: 12000 | C9: 12000 | D9: 12000 | E9: 12000 | F9: 12000 | G9: 12000 | H9: 12000 | I9: 12000 | J9: 12000 | K9: 12000 | L9: 12000 | M9: 12000 | N9: 12000 | O9: 12000 | P9: 12000 | Q9: 12000 | R9: 12000 | S9: 12000 | T9: 12000 | U9: 12000 | V9: 12000 | W9: 12000 | X9: 12000 | Y9: 12000 | Z9: =SUM(B9:Y9) -> 288000
A10: Designer (contract) | B10: 6000 | C10: 6000 | D10: 6000 | E10: 6000 | F10: 6000 | G10: 6000 | H10: 6000 | I10: 6000 | J10: 6000 | K10: 6000 | L10: 6000 | M10: 6000 | N10: 6000 | O10: 6000 | P10: 6000 | Q10: 6000 | R10: 6000 | S10: 6000 | T10: 6000 | U10: 6000 | V10: 6000 | W10: 6000 | X10: 6000 | Y10: 6000 | Z10: =SUM(B10:Y10) -> 144000
A11: Support / Ops #1 | B11: 7000 | C11: 7000 | D11: 7000 | E11: 7000 | F11: 7000 | G11: 7000 | H11: 7000 | I11: 7000 | J11: 7000 | K11: 7000 | L11: 7000 | M11: 7000 | N11: 7000 | O11: 7000 | P11: 7000 | Q11: 7000 | R11: 7000 | S11: 7000 | T11: 7000 | U11: 7000 | V11: 7000 | W11: 7000 | X11: 7000 | Y11: 7000 | Z11: =SUM(B11:Y11) -> 168000
A12: Support / Ops #2 | B12: 7000 | C12: 7000 | D12: 7000 | E12: 7000 | F12: 7000 | G12: 7000 | H12: 7000 | I12: 7000 | J12: 7000 | K12: 7000 | L12: 7000 | M12: 7000 | N12: 7000 | O12: 7000 | P12: 7000 | Q12: 7000 | R12: 7000 | S12: 7000 | T12: 7000 | U12: 7000 | V12: 7000 | W12: 7000 | X12: 7000 | Y12: 7000 | Z12: =SUM(B12:Y12) -> 168000
A14: Subtotal | B14: =SUM(B4:B13) -> 108000 | C14: =SUM(C4:C13) -> 108000 | D14: =SUM(D4:D13) -> 108000 | E14: =SUM(E4:E13) -> 108000 | F14: =SUM(F4:F13) -> 108000 | G14: =SUM(G4:G13) -> 108000 | H14: =SUM(H4:H13) -> 108000 | I14: =SUM(I4:I13) -> 108000 | ... Y14: =SUM(Y4:Y13) -> 108000 | Z14: =SUM(B14:Y14) -> 2592000

Sheet Legal_Ops_Buffer
A1: Legal / Ops / Buffer Detail (Monthly)
A3: Category | B3: Jan-26 | C3: Feb-26 | D3: Mar-26 | E3: Apr-26 | F3: May-26 | G3: Jun-26 | H3: Jul-26 | I3: Aug-26 | J3: Sep-26 | K3: Oct-26 | L3: Nov-26 | M3: Dec-26 | N3: Jan-27 | O3: Feb-27 | P3: Mar-27 | Q3: Apr-27 | R3: May-27 | S3: Jun-27 | T3: Jul-27 | U3: Aug-27 | V3: Sep-27 | W3: Oct-27 | X3: Nov-27 | Y3: Dec-27 | Z3: Total
A4: Legal & IP | B4: 4166.6667 | C4: 4166.6667 | D4: 4166.6667 | E4: 4166.6667 | F4: 4166.6667 | G4: 4166.6667 | H4: 4166.6667 | I4: 4166.6667 | J4: 4166.6667 | K4: 4166.6667 | L4: 4166.6667 | M4: 4166.6667 | N4: 4166.6667 | O4: 4166.6667 | P4: 4166.6667 | Q4: 4166.6667 | R4: 4166.6667 | S4: 4166.6667 | T4: 4166.6667 | U4: 4166.6667 | V4: 4166.6667 | W4: 4166.6667 | X4: 4166.6667 | Y4: 4166.6667 | Z4: =SUM(B4:Y4) -> 100000
A5: Accounting / Tax | B5: 2083.3333 | C5: 2083.3333 | D5: 2083.3333 | E5: 2083.3333 | F5: 2083.3333 | G5: 2083.3333 | H5: 2083.3333 | I5: 2083.3333 | J5: 2083.3333 | K5: 2083.3333 | L5: 2083.3333 | M5: 2083.3333 | N5: 2083.3333 | O5: 2083.3333 | P5: 2083.3333 | Q5: 2083.3333 | R5: 2083.3333 | S5: 2083.3333 | T5: 2083.3333 | U5: 2083.3333 | V5: 2083.3333 | W5: 2083.3333 | X5: 2083.3333 | Y5: 2083.3333 | Z5: =SUM(B5:Y5) -> 50000
A6: Insurance | B6: 2083.3333 | C6: 2083.3333 | D6: 2083.3333 | E6: 2083.3333 | F6: 2083.3333 | G6: 2083.3333 | H6: 2083.3333 | I6: 2083.3333 | J6: 2083.3333 | K6: 2083.3333 | L6: 2083.3333 | M6: 2083.3333 | N6: 2083.3333 | O6: 2083.3333 | P6: 2083.3333 | Q6: 2083.3333 | R6: 2083.3333 | S6: 2083.3333 | T6: 2083.3333 | U6: 2083.3333 | V6: 2083.3333 | W6: 2083.3333 | X6: 2083.3333 | Y6: 2083.3333 | Z6: =SUM(B6:Y6) -> 50000
A7: Software / Tools | B7: 3125 | C7: 3125 | D7: 3125 | E7: 3125 | F7: 3125 | G7: 3125 | H7: 3125 | I7: 3125 | J7: 3125 | K7: 3125 | L7: 3125 | M7: 3125 | N7: 3125 | O7: 3125 | P7: 3125 | Q7: 3125 | R7: 3125 | S7: 3125 | T7: 3125 | U7: 3125 | V7: 3125 | W7: 3125 | X7: 3125 | Y7: 3125 | Z7: =SUM(B7:Y7) -> 75000
A8: Oh-shit Buffer | B8: 5208.3333 | C8: 5208.3333 | D8: 5208.3333 | E8: 5208.3333 | F8: 5208.3333 | G8: 5208.3333 | H8: 5208.3333 | I8: 5208.3333 | J8: 5208.3333 | K8: 5208.3333 | L8: 5208.3333 | M8: 5208.3333 | N8: 5208.3333 | O8: 5208.3333 | P8: 5208.3333 | Q8: 5208.3333 | R8: 5208.3333 | S8: 5208.3333 | T8: 5208.3333 | U8: 5208.3333 | V8: 5208.3333 | W8: 5208.3333 | X8: 5208.3333 | Y8: 5208.3333 | Z8: =SUM(B8:Y8) -> 125000
A10: Subtotal | B10: =SUM(B4:B9) -> 16666.667 | C10: =SUM(C4:C9) -> 16666.667 | D10: =SUM(D4:D9) -> 16666.667 | E10: =SUM(E4:E9) -> 16666.667 | F10: =SUM(F4:F9) -> 16666.667 | G10: =SUM(G4:G9) -> 16666.667 | H10: =SUM(H4:H9) -> 16666.667 | I10: =SUM(I4:I9) -> 16666.667 | ... Y10: =SUM(Y4:Y9) -> 16666.667 | Z10: =SUM(B10:Y10) -> 400000

Sheet Cashflow_View
A1: Cashflow View (Starting Cash + EBITDA Proxy)
A3: Category | B3: Jan-26 | C3: Feb-26 | D3: Mar-26 | E3: Apr-26 | F3: May-26 | G3: Jun-26 | H3: Jul-26 | I3: Aug-26 | J3: Sep-26 | K3: Oct-26 | L3: Nov-26 | M3: Dec-26 | N3: Jan-27 | O3: Feb-27 | P3: Mar-27 | Q3: Apr-27 | R3: May-27 | S3: Jun-27 | T3: Jul-27 | U3: Aug-27 | V3: Sep-27 | W3: Oct-27 | X3: Nov-27 | Y3: Dec-27 | Z3: Total
A4: Starting Cash | B4: =Inputs_Assumptions!$B$4 -> 2500000 | C4: =B6 -> 2340000 | D4: =C6 -> 2180000 | E4: =D6 -> 2020000 | F4: =E6 -> 1860000 | G4: =F6 -> 1721250 | H4: =G6 -> 1599500 | I4: =H6 -> 1499000 | J4: =I6 -> 1419750 | ... Y4: =X6 -> 3630750
A5: EBITDA (Proxy for Net Cashflow) | B5: =Master_Proforma!B16 -> -160000 | C5: =Master_Proforma!C16 -> -160000 | D5: =Master_Proforma!D16 -> -160000 | E5: =Master_Proforma!E16 -> -160000 | F5: =Master_Proforma!F16 -> -138750 | G5: =Master_Proforma!G16 -> -121750 | H5: =Master_Proforma!H16 -> -100500 | I5: =Master_Proforma!I16 -> -79250 | ... Y5: =Master_Proforma!Y16 -> 530500 | Z5: =SUM(B5:Y5) -> 1661250
A6: Ending Cash | B6: =B4+B5 -> 2340000 | C6: =C4+C5 -> 2180000 | D6: =D4+D5 -> 2020000 | E6: =E4+E5 -> 1860000 | F6: =F4+F5 -> 1721250 | G6: =G4+G5 -> 1599500 | H6: =H4+H5 -> 1499000 | I6: =I4+I5 -> 1419750 | ... Y6: =Y4+Y5 -> 4161250 | Z6: =Y6 -> 4161250
